<annotation>
    <filename>100018.jpg</filename>
    <source>
        <annotation>ESRI ArcGIS Pro</annotation>
    </source>
    <size>
        <width>512</width>
        <height>512</height>
        <depth>3</depth>
    </size>
    <object>
        <name>0</name>
        <bndbox>
            <xmin>0.00</xmin>
            <ymin>217.48</ymin>
            <xmax>123.33</xmax>
            <ymax>308.37</ymax>
        </bndbox>
    </object>
    <object>
        <name>0</name>
        <bndbox>
            <xmin>0.00</xmin>
            <ymin>292.49</ymin>
            <xmax>105.45</xmax>
            <ymax>420.23</ymax>
        </bndbox>
    </object>
    <object>
        <name>0</name>
        <bndbox>
            <xmin>0.00</xmin>
            <ymin>410.15</ymin>
            <xmax>71.09</xmax>
            <ymax>477.72</ymax>
        </bndbox>
    </object>
    <object>
        <name>0</name>
        <bndbox>
            <xmin>0.00</xmin>
            <ymin>470.40</ymin>
            <xmax>53.13</xmax>
            <ymax>512.00</ymax>
        </bndbox>
    </object>
    <object>
        <name>0</name>
        <bndbox>
            <xmin>2.77</xmin>
            <ymin>511.14</ymin>
            <xmax>7.02</xmax>
            <ymax>512.00</ymax>
        </bndbox>
    </object>
    <object>
        <name>0</name>
        <bndbox>
            <xmin>59.55</xmin>
            <ymin>198.98</ymin>
            <xmax>132.07</xmax>
            <ymax>219.39</ymax>
        </bndbox>
    </object>
    <object>
        <name>0</name>
        <bndbox>
            <xmin>158.24</xmin>
            <ymin>208.49</ymin>
            <xmax>377.75</xmax>
            <ymax>275.71</ymax>
        </bndbox>
    </object>
    <object>
        <name>0</name>
        <bndbox>
            <xmin>152.99</xmin>
            <ymin>248.35</ymin>
            <xmax>330.16</xmax>
            <ymax>309.16</ymax>
        </bndbox>
    </object>
    <object>
        <name>0</name>
        <bndbox>
            <xmin>136.30</xmin>
            <ymin>282.85</ymin>
            <xmax>168.95</xmax>
            <ymax>325.93</ymax>
        </bndbox>
    </object>
    <object>
        <name>0</name>
        <bndbox>
            <xmin>254.70</xmin>
            <ymin>302.05</ymin>
            <xmax>327.18</xmax>
            <ymax>339.28</ymax>
        </bndbox>
    </object>
    <object>
        <name>0</name>
        <bndbox>
            <xmin>120.17</xmin>
            <ymin>328.06</ymin>
            <xmax>305.17</xmax>
            <ymax>389.33</ymax>
        </bndbox>
    </object>
    <object>
        <name>0</name>
        <bndbox>
            <xmin>115.13</xmin>
            <ymin>375.06</ymin>
            <xmax>293.64</xmax>
            <ymax>435.07</ymax>
        </bndbox>
    </object>
    <object>
        <name>0</name>
        <bndbox>
            <xmin>101.13</xmin>
            <ymin>409.56</ymin>
            <xmax>126.12</xmax>
            <ymax>441.19</ymax>
        </bndbox>
    </object>
    <object>
        <name>0</name>
        <bndbox>
            <xmin>92.26</xmin>
            <ymin>439.30</ymin>
            <xmax>280.19</xmax>
            <ymax>497.32</ymax>
        </bndbox>
    </object>
    <object>
        <name>0</name>
        <bndbox>
            <xmin>87.45</xmin>
            <ymin>470.83</ymin>
            <xmax>105.89</xmax>
            <ymax>485.70</ymax>
        </bndbox>
    </object>
    <object>
        <name>0</name>
        <bndbox>
            <xmin>113.63</xmin>
            <ymin>470.81</ymin>
            <xmax>131.30</xmax>
            <ymax>489.27</ymax>
        </bndbox>
    </object>
    <object>
        <name>0</name>
        <bndbox>
            <xmin>78.72</xmin>
            <ymin>485.70</ymin>
            <xmax>237.23</xmax>
            <ymax>512.00</ymax>
        </bndbox>
    </object>
    <object>
        <name>0</name>
        <bndbox>
            <xmin>498.59</xmin>
            <ymin>228.49</ymin>
            <xmax>512.00</xmax>
            <ymax>270.41</ymax>
        </bndbox>
    </object>
    <object>
        <name>0</name>
        <bndbox>
            <xmin>488.82</xmin>
            <ymin>228.86</ymin>
            <xmax>509.04</xmax>
            <ymax>266.50</ymax>
        </bndbox>
    </object>
    <object>
        <name>0</name>
        <bndbox>
            <xmin>463.36</xmin>
            <ymin>271.08</ymin>
            <xmax>476.84</xmax>
            <ymax>300.04</ymax>
        </bndbox>
    </object>
    <object>
        <name>0</name>
        <bndbox>
            <xmin>472.17</xmin>
            <ymin>270.67</ymin>
            <xmax>512.00</xmax>
            <ymax>311.43</ymax>
        </bndbox>
    </object>
    <object>
        <name>0</name>
        <bndbox>
            <xmin>454.64</xmin>
            <ymin>331.05</ymin>
            <xmax>512.00</xmax>
            <ymax>377.83</ymax>
        </bndbox>
    </object>
    <object>
        <name>0</name>
        <bndbox>
            <xmin>444.57</xmin>
            <ymin>333.25</ymin>
            <xmax>460.56</xmax>
            <ymax>363.69</ymax>
        </bndbox>
    </object>
    <object>
        <name>0</name>
        <bndbox>
            <xmin>436.92</xmin>
            <ymin>393.19</ymin>
            <xmax>512.00</xmax>
            <ymax>439.80</ymax>
        </bndbox>
    </object>
    <object>
        <name>0</name>
        <bndbox>
            <xmin>427.34</xmin>
            <ymin>392.18</ymin>
            <xmax>441.98</xmax>
            <ymax>423.94</ymax>
        </bndbox>
    </object>
    <object>
        <name>0</name>
        <bndbox>
            <xmin>416.89</xmin>
            <ymin>454.61</ymin>
            <xmax>512.00</xmax>
            <ymax>503.80</ymax>
        </bndbox>
    </object>
    <object>
        <name>0</name>
        <bndbox>
            <xmin>479.10</xmin>
            <ymin>503.65</ymin>
            <xmax>512.00</xmax>
            <ymax>512.00</ymax>
        </bndbox>
    </object>
    <object>
        <name>0</name>
        <bndbox>
            <xmin>408.20</xmin>
            <ymin>454.20</ymin>
            <xmax>422.85</xmax>
            <ymax>481.99</ymax>
        </bndbox>
    </object>
    <object>
        <name>0</name>
        <bndbox>
            <xmin>427.87</xmin>
            <ymin>0.00</ymin>
            <xmax>456.63</xmax>
            <ymax>32.31</ymax>
        </bndbox>
    </object>
</annotation>