<annotation>
    <filename>200056.jpg</filename>
    <source>
        <annotation>ESRI ArcGIS Pro</annotation>
    </source>
    <size>
        <width>512</width>
        <height>512</height>
        <depth>3</depth>
    </size>
    <object>
        <name>0</name>
        <bndbox>
            <xmin>0.00</xmin>
            <ymin>404.14</ymin>
            <xmax>192.11</xmax>
            <ymax>512.00</ymax>
        </bndbox>
    </object>
    <object>
        <name>0</name>
        <bndbox>
            <xmin>235.15</xmin>
            <ymin>485.30</ymin>
            <xmax>290.31</xmax>
            <ymax>512.00</ymax>
        </bndbox>
    </object>
    <object>
        <name>0</name>
        <bndbox>
            <xmin>222.53</xmin>
            <ymin>507.00</ymin>
            <xmax>234.56</xmax>
            <ymax>512.00</ymax>
        </bndbox>
    </object>
    <object>
        <name>0</name>
        <bndbox>
            <xmin>97.28</xmin>
            <ymin>0.00</ymin>
            <xmax>187.84</xmax>
            <ymax>40.07</ymax>
        </bndbox>
    </object>
    <object>
        <name>0</name>
        <bndbox>
            <xmin>0.00</xmin>
            <ymin>0.00</ymin>
            <xmax>131.60</xmax>
            <ymax>97.07</ymax>
        </bndbox>
    </object>
    <object>
        <name>0</name>
        <bndbox>
            <xmin>37.48</xmin>
            <ymin>108.90</ymin>
            <xmax>78.02</xmax>
            <ymax>145.66</ymax>
        </bndbox>
    </object>
    <object>
        <name>0</name>
        <bndbox>
            <xmin>76.65</xmin>
            <ymin>130.91</ymin>
            <xmax>102.22</xmax>
            <ymax>156.72</ymax>
        </bndbox>
    </object>
    <object>
        <name>0</name>
        <bndbox>
            <xmin>266.98</xmin>
            <ymin>213.10</ymin>
            <xmax>327.13</xmax>
            <ymax>265.71</ymax>
        </bndbox>
    </object>
    <object>
        <name>0</name>
        <bndbox>
            <xmin>308.98</xmin>
            <ymin>241.27</ymin>
            <xmax>368.62</xmax>
            <ymax>293.84</ymax>
        </bndbox>
    </object>
    <object>
        <name>3</name>
        <bndbox>
            <xmin>294.79</xmin>
            <ymin>96.55</ymin>
            <xmax>456.00</xmax>
            <ymax>209.50</ymax>
        </bndbox>
    </object>
    <object>
        <name>3</name>
        <bndbox>
            <xmin>252.04</xmin>
            <ymin>140.09</ymin>
            <xmax>412.45</xmax>
            <ymax>252.44</ymax>
        </bndbox>
    </object>
    <object>
        <name>0</name>
        <bndbox>
            <xmin>502.29</xmin>
            <ymin>502.24</ymin>
            <xmax>512.00</xmax>
            <ymax>512.00</ymax>
        </bndbox>
    </object>
</annotation>