<annotation>
    <filename>200077.jpg</filename>
    <source>
        <annotation>ESRI ArcGIS Pro</annotation>
    </source>
    <size>
        <width>512</width>
        <height>512</height>
        <depth>3</depth>
    </size>
    <object>
        <name>0</name>
        <bndbox>
            <xmin>393.12</xmin>
            <ymin>0.00</ymin>
            <xmax>512.00</xmax>
            <ymax>70.64</ymax>
        </bndbox>
    </object>
    <object>
        <name>0</name>
        <bndbox>
            <xmin>454.62</xmin>
            <ymin>0.00</ymin>
            <xmax>512.00</xmax>
            <ymax>37.55</ymax>
        </bndbox>
    </object>
    <object>
        <name>0</name>
        <bndbox>
            <xmin>455.77</xmin>
            <ymin>66.10</ymin>
            <xmax>501.91</xmax>
            <ymax>109.28</ymax>
        </bndbox>
    </object>
    <object>
        <name>0</name>
        <bndbox>
            <xmin>435.52</xmin>
            <ymin>92.62</ymin>
            <xmax>469.18</xmax>
            <ymax>121.32</ymax>
        </bndbox>
    </object>
    <object>
        <name>0</name>
        <bndbox>
            <xmin>409.08</xmin>
            <ymin>41.45</ymin>
            <xmax>480.94</xmax>
            <ymax>101.08</ymax>
        </bndbox>
    </object>
    <object>
        <name>0</name>
        <bndbox>
            <xmin>340.57</xmin>
            <ymin>0.00</ymin>
            <xmax>442.74</xmax>
            <ymax>63.75</ymax>
        </bndbox>
    </object>
    <object>
        <name>0</name>
        <bndbox>
            <xmin>288.00</xmin>
            <ymin>0.00</ymin>
            <xmax>340.38</xmax>
            <ymax>28.04</ymax>
        </bndbox>
    </object>
    <object>
        <name>0</name>
        <bndbox>
            <xmin>320.13</xmin>
            <ymin>16.15</ymin>
            <xmax>415.71</xmax>
            <ymax>86.90</ymax>
        </bndbox>
    </object>
    <object>
        <name>0</name>
        <bndbox>
            <xmin>0.00</xmin>
            <ymin>429.73</ymin>
            <xmax>48.13</xmax>
            <ymax>491.73</ymax>
        </bndbox>
    </object>
    <object>
        <name>0</name>
        <bndbox>
            <xmin>24.43</xmin>
            <ymin>471.71</ymin>
            <xmax>88.87</xmax>
            <ymax>512.00</ymax>
        </bndbox>
    </object>
    <object>
        <name>0</name>
        <bndbox>
            <xmin>15.04</xmin>
            <ymin>502.73</ymin>
            <xmax>35.76</xmax>
            <ymax>512.00</ymax>
        </bndbox>
    </object>
</annotation>