<annotation>
    <filename>200132.jpg</filename>
    <source>
        <annotation>ESRI ArcGIS Pro</annotation>
    </source>
    <size>
        <width>512</width>
        <height>512</height>
        <depth>3</depth>
    </size>
    <object>
        <name>0</name>
        <bndbox>
            <xmin>30.81</xmin>
            <ymin>0.00</ymin>
            <xmax>174.96</xmax>
            <ymax>57.88</ymax>
        </bndbox>
    </object>
    <object>
        <name>0</name>
        <bndbox>
            <xmin>0.00</xmin>
            <ymin>5.43</ymin>
            <xmax>43.77</xmax>
            <ymax>78.05</ymax>
        </bndbox>
    </object>
    <object>
        <name>0</name>
        <bndbox>
            <xmin>244.35</xmin>
            <ymin>0.00</ymin>
            <xmax>512.00</xmax>
            <ymax>173.18</ymax>
        </bndbox>
    </object>
    <object>
        <name>0</name>
        <bndbox>
            <xmin>189.87</xmin>
            <ymin>12.56</ymin>
            <xmax>433.41</xmax>
            <ymax>182.29</ymax>
        </bndbox>
    </object>
    <object>
        <name>0</name>
        <bndbox>
            <xmin>106.83</xmin>
            <ymin>69.07</ymin>
            <xmax>311.46</xmax>
            <ymax>207.08</ymax>
        </bndbox>
    </object>
    <object>
        <name>0</name>
        <bndbox>
            <xmin>260.90</xmin>
            <ymin>180.31</ymin>
            <xmax>376.30</xmax>
            <ymax>268.35</ymax>
        </bndbox>
    </object>
    <object>
        <name>0</name>
        <bndbox>
            <xmin>366.98</xmin>
            <ymin>213.03</ymin>
            <xmax>483.38</xmax>
            <ymax>303.73</ymax>
        </bndbox>
    </object>
    <object>
        <name>0</name>
        <bndbox>
            <xmin>182.61</xmin>
            <ymin>269.47</ymin>
            <xmax>264.99</xmax>
            <ymax>328.37</ymax>
        </bndbox>
    </object>
    <object>
        <name>0</name>
        <bndbox>
            <xmin>346.38</xmin>
            <ymin>392.70</ymin>
            <xmax>397.41</xmax>
            <ymax>441.65</ymax>
        </bndbox>
    </object>
    <object>
        <name>0</name>
        <bndbox>
            <xmin>0.00</xmin>
            <ymin>250.22</ymin>
            <xmax>222.97</xmax>
            <ymax>433.81</ymax>
        </bndbox>
    </object>
    <object>
        <name>0</name>
        <bndbox>
            <xmin>91.50</xmin>
            <ymin>425.62</ymin>
            <xmax>169.35</xmax>
            <ymax>499.18</ymax>
        </bndbox>
    </object>
    <object>
        <name>0</name>
        <bndbox>
            <xmin>211.87</xmin>
            <ymin>464.60</ymin>
            <xmax>318.28</xmax>
            <ymax>512.00</ymax>
        </bndbox>
    </object>
    <object>
        <name>0</name>
        <bndbox>
            <xmin>31.62</xmin>
            <ymin>461.55</ymin>
            <xmax>98.99</xmax>
            <ymax>512.00</ymax>
        </bndbox>
    </object>
    <object>
        <name>3</name>
        <bndbox>
            <xmin>0.00</xmin>
            <ymin>384.96</ymin>
            <xmax>28.72</xmax>
            <ymax>434.21</ymax>
        </bndbox>
    </object>
    <object>
        <name>3</name>
        <bndbox>
            <xmin>0.00</xmin>
            <ymin>325.54</ymin>
            <xmax>5.81</xmax>
            <ymax>334.28</ymax>
        </bndbox>
    </object>
</annotation>