<annotation>
    <filename>200157.jpg</filename>
    <source>
        <annotation>ESRI ArcGIS Pro</annotation>
    </source>
    <size>
        <width>512</width>
        <height>512</height>
        <depth>3</depth>
    </size>
    <object>
        <name>0</name>
        <bndbox>
            <xmin>383.59</xmin>
            <ymin>414.92</ymin>
            <xmax>512.00</xmax>
            <ymax>512.00</ymax>
        </bndbox>
    </object>
    <object>
        <name>3</name>
        <bndbox>
            <xmin>455.98</xmin>
            <ymin>0.00</ymin>
            <xmax>512.00</xmax>
            <ymax>36.53</ymax>
        </bndbox>
    </object>
    <object>
        <name>0</name>
        <bndbox>
            <xmin>157.02</xmin>
            <ymin>421.94</ymin>
            <xmax>285.30</xmax>
            <ymax>512.00</ymax>
        </bndbox>
    </object>
    <object>
        <name>3</name>
        <bndbox>
            <xmin>179.08</xmin>
            <ymin>90.90</ymin>
            <xmax>512.00</xmax>
            <ymax>389.54</ymax>
        </bndbox>
    </object>
    <object>
        <name>3</name>
        <bndbox>
            <xmin>114.08</xmin>
            <ymin>22.37</ymin>
            <xmax>237.65</xmax>
            <ymax>136.54</ymax>
        </bndbox>
    </object>
    <object>
        <name>3</name>
        <bndbox>
            <xmin>437.74</xmin>
            <ymin>306.99</ymin>
            <xmax>512.00</xmax>
            <ymax>411.14</ymax>
        </bndbox>
    </object>
    <object>
        <name>3</name>
        <bndbox>
            <xmin>464.73</xmin>
            <ymin>393.84</ymin>
            <xmax>512.00</xmax>
            <ymax>456.42</ymax>
        </bndbox>
    </object>
</annotation>