<annotation>
    <filename>300106.jpg</filename>
    <source>
        <annotation>ESRI ArcGIS Pro</annotation>
    </source>
    <size>
        <width>512</width>
        <height>512</height>
        <depth>3</depth>
    </size>
    <object>
        <name>2</name>
        <bndbox>
            <xmin>0.00</xmin>
            <ymin>41.09</ymin>
            <xmax>44.19</xmax>
            <ymax>336.10</ymax>
        </bndbox>
    </object>
    <object>
        <name>2</name>
        <bndbox>
            <xmin>49.86</xmin>
            <ymin>50.17</ymin>
            <xmax>122.70</xmax>
            <ymax>345.37</ymax>
        </bndbox>
    </object>
    <object>
        <name>2</name>
        <bndbox>
            <xmin>9.82</xmin>
            <ymin>132.57</ymin>
            <xmax>72.64</xmax>
            <ymax>341.13</ymax>
        </bndbox>
    </object>
    <object>
        <name>2</name>
        <bndbox>
            <xmin>85.04</xmin>
            <ymin>55.79</ymin>
            <xmax>158.62</xmax>
            <ymax>350.53</ymax>
        </bndbox>
    </object>
    <object>
        <name>2</name>
        <bndbox>
            <xmin>115.85</xmin>
            <ymin>68.83</ymin>
            <xmax>190.15</xmax>
            <ymax>351.74</ymax>
        </bndbox>
    </object>
    <object>
        <name>2</name>
        <bndbox>
            <xmin>166.57</xmin>
            <ymin>69.09</ymin>
            <xmax>235.81</xmax>
            <ymax>339.63</ymax>
        </bndbox>
    </object>
    <object>
        <name>2</name>
        <bndbox>
            <xmin>199.71</xmin>
            <ymin>70.52</ymin>
            <xmax>251.93</xmax>
            <ymax>351.77</ymax>
        </bndbox>
    </object>
    <object>
        <name>2</name>
        <bndbox>
            <xmin>211.17</xmin>
            <ymin>71.23</ymin>
            <xmax>262.06</xmax>
            <ymax>354.58</ymax>
        </bndbox>
    </object>
    <object>
        <name>2</name>
        <bndbox>
            <xmin>222.60</xmin>
            <ymin>72.40</ymin>
            <xmax>272.81</xmax>
            <ymax>358.51</ymax>
        </bndbox>
    </object>
    <object>
        <name>0</name>
        <bndbox>
            <xmin>293.07</xmin>
            <ymin>66.13</ymin>
            <xmax>314.54</xmax>
            <ymax>78.65</ymax>
        </bndbox>
    </object>
    <object>
        <name>0</name>
        <bndbox>
            <xmin>160.47</xmin>
            <ymin>345.71</ymin>
            <xmax>177.72</xmax>
            <ymax>355.82</ymax>
        </bndbox>
    </object>
    <object>
        <name>2</name>
        <bndbox>
            <xmin>231.26</xmin>
            <ymin>215.38</ymin>
            <xmax>296.10</xmax>
            <ymax>357.92</ymax>
        </bndbox>
    </object>
    <object>
        <name>3</name>
        <bndbox>
            <xmin>347.77</xmin>
            <ymin>299.35</ymin>
            <xmax>363.20</xmax>
            <ymax>351.21</ymax>
        </bndbox>
    </object>
    <object>
        <name>3</name>
        <bndbox>
            <xmin>355.40</xmin>
            <ymin>288.41</ymin>
            <xmax>396.04</xmax>
            <ymax>299.20</ymax>
        </bndbox>
    </object>
    <object>
        <name>3</name>
        <bndbox>
            <xmin>360.76</xmin>
            <ymin>263.18</ymin>
            <xmax>398.89</xmax>
            <ymax>273.14</ymax>
        </bndbox>
    </object>
    <object>
        <name>3</name>
        <bndbox>
            <xmin>357.20</xmin>
            <ymin>252.01</ymin>
            <xmax>363.29</xmax>
            <ymax>259.77</ymax>
        </bndbox>
    </object>
</annotation>