<annotation>
    <filename>400104.jpg</filename>
    <source>
        <annotation>ESRI ArcGIS Pro</annotation>
    </source>
    <size>
        <width>512</width>
        <height>512</height>
        <depth>3</depth>
    </size>
    <object>
        <name>3</name>
        <bndbox>
            <xmin>0.00</xmin>
            <ymin>487.90</ymin>
            <xmax>10.76</xmax>
            <ymax>508.25</ymax>
        </bndbox>
    </object>
    <object>
        <name>3</name>
        <bndbox>
            <xmin>29.30</xmin>
            <ymin>484.65</ymin>
            <xmax>265.58</xmax>
            <ymax>512.00</ymax>
        </bndbox>
    </object>
    <object>
        <name>3</name>
        <bndbox>
            <xmin>22.99</xmin>
            <ymin>400.12</ymin>
            <xmax>265.79</xmax>
            <ymax>447.07</ymax>
        </bndbox>
    </object>
    <object>
        <name>3</name>
        <bndbox>
            <xmin>17.28</xmin>
            <ymin>428.68</ymin>
            <xmax>266.30</xmax>
            <ymax>474.30</ymax>
        </bndbox>
    </object>
    <object>
        <name>3</name>
        <bndbox>
            <xmin>15.02</xmin>
            <ymin>458.48</ymin>
            <xmax>268.35</xmax>
            <ymax>503.36</ymax>
        </bndbox>
    </object>
    <object>
        <name>3</name>
        <bndbox>
            <xmin>273.49</xmin>
            <ymin>371.16</ymin>
            <xmax>511.77</xmax>
            <ymax>422.05</ymax>
        </bndbox>
    </object>
    <object>
        <name>3</name>
        <bndbox>
            <xmin>277.97</xmin>
            <ymin>403.63</ymin>
            <xmax>512.00</xmax>
            <ymax>449.01</ymax>
        </bndbox>
    </object>
    <object>
        <name>3</name>
        <bndbox>
            <xmin>279.85</xmin>
            <ymin>426.97</ymin>
            <xmax>512.00</xmax>
            <ymax>478.11</ymax>
        </bndbox>
    </object>
    <object>
        <name>3</name>
        <bndbox>
            <xmin>280.80</xmin>
            <ymin>455.97</ymin>
            <xmax>512.00</xmax>
            <ymax>500.76</ymax>
        </bndbox>
    </object>
    <object>
        <name>3</name>
        <bndbox>
            <xmin>287.91</xmin>
            <ymin>496.83</ymin>
            <xmax>410.02</xmax>
            <ymax>512.00</ymax>
        </bndbox>
    </object>
    <object>
        <name>3</name>
        <bndbox>
            <xmin>413.02</xmin>
            <ymin>483.00</ymin>
            <xmax>512.00</xmax>
            <ymax>512.00</ymax>
        </bndbox>
    </object>
</annotation>