<annotation>
    <filename>400140.jpg</filename>
    <source>
        <annotation>ESRI ArcGIS Pro</annotation>
    </source>
    <size>
        <width>512</width>
        <height>512</height>
        <depth>3</depth>
    </size>
    <object>
        <name>3</name>
        <bndbox>
            <xmin>52.90</xmin>
            <ymin>0.00</ymin>
            <xmax>167.84</xmax>
            <ymax>13.05</ymax>
        </bndbox>
    </object>
    <object>
        <name>3</name>
        <bndbox>
            <xmin>34.46</xmin>
            <ymin>0.00</ymin>
            <xmax>224.09</xmax>
            <ymax>44.56</ymax>
        </bndbox>
    </object>
    <object>
        <name>3</name>
        <bndbox>
            <xmin>53.22</xmin>
            <ymin>50.42</ymin>
            <xmax>289.27</xmax>
            <ymax>100.50</ymax>
        </bndbox>
    </object>
    <object>
        <name>3</name>
        <bndbox>
            <xmin>59.16</xmin>
            <ymin>78.31</ymin>
            <xmax>291.70</xmax>
            <ymax>124.18</ymax>
        </bndbox>
    </object>
    <object>
        <name>3</name>
        <bndbox>
            <xmin>47.74</xmin>
            <ymin>104.48</ymin>
            <xmax>297.84</xmax>
            <ymax>155.69</ymax>
        </bndbox>
    </object>
    <object>
        <name>3</name>
        <bndbox>
            <xmin>44.17</xmin>
            <ymin>161.35</ymin>
            <xmax>56.61</xmax>
            <ymax>175.30</ymax>
        </bndbox>
    </object>
    <object>
        <name>3</name>
        <bndbox>
            <xmin>47.95</xmin>
            <ymin>154.86</ymin>
            <xmax>301.73</xmax>
            <ymax>205.72</ymax>
        </bndbox>
    </object>
    <object>
        <name>3</name>
        <bndbox>
            <xmin>60.79</xmin>
            <ymin>186.27</ymin>
            <xmax>306.52</xmax>
            <ymax>233.78</ymax>
        </bndbox>
    </object>
    <object>
        <name>3</name>
        <bndbox>
            <xmin>57.23</xmin>
            <ymin>263.37</ymin>
            <xmax>311.73</xmax>
            <ymax>314.15</ymax>
        </bndbox>
    </object>
    <object>
        <name>3</name>
        <bndbox>
            <xmin>51.97</xmin>
            <ymin>228.39</ymin>
            <xmax>308.08</xmax>
            <ymax>278.14</ymax>
        </bndbox>
    </object>
    <object>
        <name>3</name>
        <bndbox>
            <xmin>299.83</xmin>
            <ymin>0.00</ymin>
            <xmax>429.40</xmax>
            <ymax>15.71</ymax>
        </bndbox>
    </object>
    <object>
        <name>3</name>
        <bndbox>
            <xmin>323.40</xmin>
            <ymin>26.06</ymin>
            <xmax>512.00</xmax>
            <ymax>70.28</ymax>
        </bndbox>
    </object>
    <object>
        <name>3</name>
        <bndbox>
            <xmin>328.99</xmin>
            <ymin>80.58</ymin>
            <xmax>512.00</xmax>
            <ymax>122.26</ymax>
        </bndbox>
    </object>
    <object>
        <name>3</name>
        <bndbox>
            <xmin>333.75</xmin>
            <ymin>107.83</ymin>
            <xmax>512.00</xmax>
            <ymax>142.33</ymax>
        </bndbox>
    </object>
    <object>
        <name>3</name>
        <bndbox>
            <xmin>343.39</xmin>
            <ymin>183.52</ymin>
            <xmax>512.00</xmax>
            <ymax>222.37</ymax>
        </bndbox>
    </object>
    <object>
        <name>3</name>
        <bndbox>
            <xmin>345.53</xmin>
            <ymin>219.53</ymin>
            <xmax>512.00</xmax>
            <ymax>261.34</ymax>
        </bndbox>
    </object>
    <object>
        <name>3</name>
        <bndbox>
            <xmin>328.40</xmin>
            <ymin>255.43</ymin>
            <xmax>512.00</xmax>
            <ymax>296.44</ymax>
        </bndbox>
    </object>
    <object>
        <name>3</name>
        <bndbox>
            <xmin>329.82</xmin>
            <ymin>292.11</ymin>
            <xmax>512.00</xmax>
            <ymax>330.18</ymax>
        </bndbox>
    </object>
</annotation>