<annotation>
    <filename>400138.jpg</filename>
    <source>
        <annotation>ESRI ArcGIS Pro</annotation>
    </source>
    <size>
        <width>512</width>
        <height>512</height>
        <depth>3</depth>
    </size>
    <object>
        <name>3</name>
        <bndbox>
            <xmin>8.95</xmin>
            <ymin>0.00</ymin>
            <xmax>232.43</xmax>
            <ymax>24.72</ymax>
        </bndbox>
    </object>
    <object>
        <name>3</name>
        <bndbox>
            <xmin>16.74</xmin>
            <ymin>5.70</ymin>
            <xmax>257.94</xmax>
            <ymax>51.01</ymax>
        </bndbox>
    </object>
    <object>
        <name>3</name>
        <bndbox>
            <xmin>14.60</xmin>
            <ymin>32.83</ymin>
            <xmax>247.25</xmax>
            <ymax>78.16</ymax>
        </bndbox>
    </object>
    <object>
        <name>3</name>
        <bndbox>
            <xmin>42.44</xmin>
            <ymin>75.66</ymin>
            <xmax>138.05</xmax>
            <ymax>104.69</ymax>
        </bndbox>
    </object>
    <object>
        <name>3</name>
        <bndbox>
            <xmin>20.31</xmin>
            <ymin>103.50</ymin>
            <xmax>143.60</xmax>
            <ymax>134.38</ymax>
        </bndbox>
    </object>
    <object>
        <name>3</name>
        <bndbox>
            <xmin>149.51</xmin>
            <ymin>90.65</ymin>
            <xmax>262.79</xmax>
            <ymax>120.11</ymax>
        </bndbox>
    </object>
    <object>
        <name>3</name>
        <bndbox>
            <xmin>24.59</xmin>
            <ymin>122.77</ymin>
            <xmax>207.72</xmax>
            <ymax>165.52</ymax>
        </bndbox>
    </object>
    <object>
        <name>3</name>
        <bndbox>
            <xmin>142.94</xmin>
            <ymin>63.11</ymin>
            <xmax>259.15</xmax>
            <ymax>93.95</ymax>
        </bndbox>
    </object>
    <object>
        <name>3</name>
        <bndbox>
            <xmin>44.79</xmin>
            <ymin>152.75</ymin>
            <xmax>209.85</xmax>
            <ymax>186.75</ymax>
        </bndbox>
    </object>
    <object>
        <name>3</name>
        <bndbox>
            <xmin>24.51</xmin>
            <ymin>173.21</ymin>
            <xmax>39.03</xmax>
            <ymax>191.78</ymax>
        </bndbox>
    </object>
    <object>
        <name>3</name>
        <bndbox>
            <xmin>31.08</xmin>
            <ymin>174.93</ymin>
            <xmax>213.55</xmax>
            <ymax>215.57</ymax>
        </bndbox>
    </object>
    <object>
        <name>3</name>
        <bndbox>
            <xmin>31.37</xmin>
            <ymin>202.91</ymin>
            <xmax>218.55</xmax>
            <ymax>247.76</ymax>
        </bndbox>
    </object>
    <object>
        <name>3</name>
        <bndbox>
            <xmin>52.31</xmin>
            <ymin>231.61</ymin>
            <xmax>221.91</xmax>
            <ymax>269.05</ymax>
        </bndbox>
    </object>
    <object>
        <name>3</name>
        <bndbox>
            <xmin>34.46</xmin>
            <ymin>255.26</ymin>
            <xmax>224.09</xmax>
            <ymax>300.56</ymax>
        </bndbox>
    </object>
    <object>
        <name>3</name>
        <bndbox>
            <xmin>53.22</xmin>
            <ymin>306.42</ymin>
            <xmax>289.27</xmax>
            <ymax>356.50</ymax>
        </bndbox>
    </object>
    <object>
        <name>3</name>
        <bndbox>
            <xmin>59.16</xmin>
            <ymin>334.31</ymin>
            <xmax>291.70</xmax>
            <ymax>380.18</ymax>
        </bndbox>
    </object>
    <object>
        <name>3</name>
        <bndbox>
            <xmin>47.74</xmin>
            <ymin>360.48</ymin>
            <xmax>297.84</xmax>
            <ymax>411.69</ymax>
        </bndbox>
    </object>
    <object>
        <name>3</name>
        <bndbox>
            <xmin>44.17</xmin>
            <ymin>417.35</ymin>
            <xmax>56.61</xmax>
            <ymax>431.30</ymax>
        </bndbox>
    </object>
    <object>
        <name>3</name>
        <bndbox>
            <xmin>47.95</xmin>
            <ymin>410.86</ymin>
            <xmax>301.73</xmax>
            <ymax>461.72</ymax>
        </bndbox>
    </object>
    <object>
        <name>3</name>
        <bndbox>
            <xmin>60.79</xmin>
            <ymin>442.27</ymin>
            <xmax>306.52</xmax>
            <ymax>489.78</ymax>
        </bndbox>
    </object>
    <object>
        <name>3</name>
        <bndbox>
            <xmin>54.75</xmin>
            <ymin>484.39</ymin>
            <xmax>308.08</xmax>
            <ymax>512.00</ymax>
        </bndbox>
    </object>
    <object>
        <name>3</name>
        <bndbox>
            <xmin>285.00</xmin>
            <ymin>0.00</ymin>
            <xmax>479.42</xmax>
            <ymax>22.13</ymax>
        </bndbox>
    </object>
    <object>
        <name>3</name>
        <bndbox>
            <xmin>290.71</xmin>
            <ymin>28.70</ymin>
            <xmax>512.00</xmax>
            <ymax>74.78</ymax>
        </bndbox>
    </object>
    <object>
        <name>3</name>
        <bndbox>
            <xmin>280.71</xmin>
            <ymin>58.01</ymin>
            <xmax>512.00</xmax>
            <ymax>105.76</ymax>
        </bndbox>
    </object>
    <object>
        <name>3</name>
        <bndbox>
            <xmin>321.64</xmin>
            <ymin>85.66</ymin>
            <xmax>512.00</xmax>
            <ymax>129.54</ymax>
        </bndbox>
    </object>
    <object>
        <name>3</name>
        <bndbox>
            <xmin>286.42</xmin>
            <ymin>112.85</ymin>
            <xmax>512.00</xmax>
            <ymax>158.65</ymax>
        </bndbox>
    </object>
    <object>
        <name>3</name>
        <bndbox>
            <xmin>341.63</xmin>
            <ymin>170.79</ymin>
            <xmax>512.00</xmax>
            <ymax>207.64</ymax>
        </bndbox>
    </object>
    <object>
        <name>3</name>
        <bndbox>
            <xmin>307.36</xmin>
            <ymin>195.46</ymin>
            <xmax>512.00</xmax>
            <ymax>241.63</ymax>
        </bndbox>
    </object>
    <object>
        <name>3</name>
        <bndbox>
            <xmin>299.27</xmin>
            <ymin>225.25</ymin>
            <xmax>512.00</xmax>
            <ymax>271.71</ymax>
        </bndbox>
    </object>
    <object>
        <name>3</name>
        <bndbox>
            <xmin>298.80</xmin>
            <ymin>141.55</ymin>
            <xmax>512.00</xmax>
            <ymax>188.56</ymax>
        </bndbox>
    </object>
    <object>
        <name>3</name>
        <bndbox>
            <xmin>323.40</xmin>
            <ymin>282.06</ymin>
            <xmax>512.00</xmax>
            <ymax>326.28</ymax>
        </bndbox>
    </object>
    <object>
        <name>3</name>
        <bndbox>
            <xmin>328.99</xmin>
            <ymin>336.58</ymin>
            <xmax>512.00</xmax>
            <ymax>378.26</ymax>
        </bndbox>
    </object>
    <object>
        <name>3</name>
        <bndbox>
            <xmin>333.75</xmin>
            <ymin>363.83</ymin>
            <xmax>512.00</xmax>
            <ymax>398.33</ymax>
        </bndbox>
    </object>
    <object>
        <name>3</name>
        <bndbox>
            <xmin>343.39</xmin>
            <ymin>439.52</ymin>
            <xmax>512.00</xmax>
            <ymax>478.37</ymax>
        </bndbox>
    </object>
    <object>
        <name>3</name>
        <bndbox>
            <xmin>345.53</xmin>
            <ymin>475.53</ymin>
            <xmax>512.00</xmax>
            <ymax>512.00</ymax>
        </bndbox>
    </object>
    <object>
        <name>3</name>
        <bndbox>
            <xmin>506.91</xmin>
            <ymin>511.43</ymin>
            <xmax>512.00</xmax>
            <ymax>512.00</ymax>
        </bndbox>
    </object>
</annotation>